odoo/addons/purchase_request_operating_unit_access_all/README.rst
odoo/addons/purchase_request_operating_unit_access_all/__init__.py
odoo/addons/purchase_request_operating_unit_access_all/__manifest__.py
odoo/addons/purchase_request_operating_unit_access_all/i18n/it.po
odoo/addons/purchase_request_operating_unit_access_all/i18n/purchase_request_operating_unit_access_all.pot
odoo/addons/purchase_request_operating_unit_access_all/readme/CONFIGURE.rst
odoo/addons/purchase_request_operating_unit_access_all/readme/CONTRIBUTORS.rst
odoo/addons/purchase_request_operating_unit_access_all/readme/DESCRIPTION.rst
odoo/addons/purchase_request_operating_unit_access_all/security/purchase_security.xml
odoo/addons/purchase_request_operating_unit_access_all/static/description/icon.png
odoo/addons/purchase_request_operating_unit_access_all/static/description/index.html
odoo14_addon_purchase_request_operating_unit_access_all-14.0.1.0.1.dev5.dist-info/METADATA
odoo14_addon_purchase_request_operating_unit_access_all-14.0.1.0.1.dev5.dist-info/WHEEL
odoo14_addon_purchase_request_operating_unit_access_all-14.0.1.0.1.dev5.dist-info/top_level.txt
odoo14_addon_purchase_request_operating_unit_access_all-14.0.1.0.1.dev5.dist-info/RECORD
